CHANGES.rst
LICENSE
MANIFEST.in
README
README.rst
requirements.txt
setup.py
ctrie/__init__.py
ctrie.egg-info/PKG-INFO
ctrie.egg-info/SOURCES.txt
ctrie.egg-info/dependency_links.txt
ctrie.egg-info/top_level.txt