Metadata-Version: 1.1
Name: ctrie
Version: 0.1.0
Summary: compact tries for Python
Home-page: https://github.com/bfontaine/ctrie
Author: Baptiste Fontaine
Author-email: b@ptistefontaine.fr
License: Copyright © 2014 – Baptiste Fontaine
